{
    "model_name": "GSPHAR_24_magnet_dynamic_h1_standard_mse_best_val0.1589",
    "validation_loss": 0.15887485654093325,
    "timestamp": "2025-05-12 23:14:22",
    "horizon": 1,
    "filter_size": 24,
    "epochs_trained": 3,
    "resumed_from": null,
    "tag": "standard_mse",
    "train_loss_history": [
        1.0464580965042114,
        0.44782022247711817,
        0.20436312993367514
    ],
    "test_loss_history": [
        0.5603456264361739,
        0.1646734792739153,
        0.15887485654093325
    ],
    "learning_rate": 0.01,
    "batch_size": 32,
    "patience": 200,
    "input_dim": 3,
    "output_dim": 1,
    "look_back": 22,
    "loss_function": "mse",
    "loss_function_params": {
        "threshold": null,
        "weight_factor": null,
        "under_prediction_factor": null,
        "thresholds": null,
        "weights": null,
        "mse_weight": null,
        "large_jump_weight": null
    }
}